csv2vcard/__init__.py
csv2vcard/__main__.py
csv2vcard/cli.py
csv2vcard/create_vcard.py
csv2vcard/csv2vcard.py
csv2vcard/exceptions.py
csv2vcard/export_vcard.py
csv2vcard/mapping.py
csv2vcard/models.py
csv2vcard/parse_csv.py
csv2vcard/py.typed
csv2vcard/validators.py
csv2vcard-0.4.0.dist-info/licenses/LICENSE.txt
csv2vcard-0.4.0.dist-info/METADATA
csv2vcard-0.4.0.dist-info/WHEEL
csv2vcard-0.4.0.dist-info/entry_points.txt
csv2vcard-0.4.0.dist-info/top_level.txt
csv2vcard-0.4.0.dist-info/RECORD
