Metadata-Version: 2.4
Name: csv2vcard
Version: 0.4.0
Summary: A library for converting CSVs to vCards (vCard 3.0 and 4.0)
Home-page: https://github.com/tech4242/csv2vcard
Author: tech4242
License-Expression: MIT
Project-URL: Homepage, https://github.com/tech4242/csv2vcard
Project-URL: Bug Tracker, https://github.com/tech4242/csv2vcard/issues
Keywords: csv,vcard,contacts,export,vcf
Classifier: Development Status :: 4 - Beta
Classifier: Programming Language :: Python :: 3
Classifier: Programming Language :: Python :: 3.9
Classifier: Programming Language :: Python :: 3.10
Classifier: Programming Language :: Python :: 3.11
Classifier: Programming Language :: Python :: 3.12
Classifier: Programming Language :: Python :: 3.13
Classifier: Typing :: Typed
Classifier: Operating System :: OS Independent
Classifier: Topic :: Utilities
Requires-Python: >=3.9
License-File: LICENSE.txt
Provides-Extra: cli
Requires-Dist: typer>=0.9.0; extra == "cli"
Provides-Extra: encoding
Requires-Dist: charset-normalizer>=3.0.0; extra == "encoding"
Provides-Extra: all
Requires-Dist: typer>=0.9.0; extra == "all"
Requires-Dist: charset-normalizer>=3.0.0; extra == "all"
Provides-Extra: dev
Requires-Dist: pytest>=7.0; extra == "dev"
Requires-Dist: pytest-cov>=4.0; extra == "dev"
Requires-Dist: mypy>=1.0; extra == "dev"
Requires-Dist: ruff>=0.1.0; extra == "dev"
Requires-Dist: typer>=0.9.0; extra == "dev"
Requires-Dist: charset-normalizer>=3.0.0; extra == "dev"
Dynamic: home-page
Dynamic: license-file
Dynamic: requires-python
